Metadata-Version: 2.1
Name: invoicing-xl-pdf-v
Version: 1.0.0
Summary: Convert Excel invoices to PDF invoices using this package.
Home-page: https://example.com
Author: Vedasree R
Author-email: vedaraja17@gmail.com
License: MIT
Keywords: invoice,excel,pdf
Classifier: Development Status :: 3 - Alpha
Classifier: Intended Audience :: Developers
Classifier: Topic :: Software Development :: Build Tools
Classifier: License :: OSI Approved :: MIT License
Classifier: Programming Language :: Python :: 3.8
Classifier: Programming Language :: Python :: 3.9
Classifier: Programming Language :: Python :: 3.10
Classifier: Programming Language :: Python :: 3.11
